Metadata-Version: 2.1
Name: python-trading212
Version: 2.0.4
Summary: An unofficial client for the official Trading212 API
Home-page: https://github.com/jcoelho93/python-trading212
License: MIT
Keywords: python,trading212,api,client,unofficial,finance,stocks,trading
Author: José Coelho
Author-email: 16445494+jcoelho93@users.noreply.github.com
Requires-Python: >=3.12,<4.0
Classifier: Framework :: Pydantic
Classifier: License :: OSI Approved :: MIT License
Classifier: Programming Language :: Python :: 3
Classifier: Programming Language :: Python :: 3.12
Classifier: Topic :: Office/Business :: Financial :: Investment
Requires-Dist: pydantic (>=2.7.1,<3.0.0)
Requires-Dist: requests (>=2.31.0,<3.0.0)
Project-URL: Bug Tracker, https://github.com/jcoelho93/python-trading212/issues
Project-URL: Documentation, https://github.com/jcoelho93/python-trading212
Project-URL: Repository, https://github.com/jcoelho93/python-trading212
